{
  "os":  "macOS-26.5.1-arm64-arm-64bit",
  "python":  "CPython 3.9.6",
  "startedAt":  "2026-07-15T22:30:04.323883Z",
  "program":  "<python with no main file>",
  "git":  {
    "remote":  "https://github.com/singhh5050/delta-attention.git",
    "commit":  "a9f5b57f24dc5a620c3beab975a522d91383456a"
  },
  "email":  "singhh5050@gmail.com",
  "root":  "/Users/harshvardhan@nvidia.com/Development/delta-attention/repo",
  "host":  "H766QV2N26",
  "executable":  "/Library/Developer/CommandLineTools/usr/bin/python3",
  "cpu_count":  18,
  "cpu_count_logical":  18,
  "disk":  {
    "/":  {
      "total":  "994610155520",
      "used":  "182002532352"
    }
  },
  "memory":  {
    "total":  "51539607552"
  },
  "apple":  {},
  "writerId":  "1stv1w0uec35yxp1svv8fsqdu4tl6r8n"
}